snutree/__init__.py
snutree/__main__.py
snutree/api.py
snutree/cli.py
snutree/errors.py
snutree/gui.py
snutree/tree.py
snutree/readers/__init__.py
snutree/readers/csv.py
snutree/readers/dot.py
snutree/readers/sql.py
snutree/schemas/__init__.py
snutree/schemas/basic.py
snutree/schemas/chapter.py
snutree/schemas/keyed.py
snutree/schemas/sigmanu.py
snutree/utilities/__init__.py
snutree/utilities/cerberus.py
snutree/utilities/colors.py
snutree/utilities/dot.py
snutree/utilities/indent.py
snutree/utilities/logging.py
snutree/utilities/semester.py
snutree/utilities/voluptuous.py
snutree/writers/__init__.py
snutree/writers/dot.py
snutree/writers/stats.py
snutree/writers/table.py
snutree-0.3.0.dist-info/DESCRIPTION.rst
snutree-0.3.0.dist-info/METADATA
snutree-0.3.0.dist-info/RECORD
snutree-0.3.0.dist-info/WHEEL
snutree-0.3.0.dist-info/entry_points.txt
snutree-0.3.0.dist-info/metadata.json
snutree-0.3.0.dist-info/top_level.txt
