Metadata-Version: 2.0
Name: snutree
Version: 0.3.0
Summary: Visualize big–little brother/sister relationships in Greek-letter organizations
Home-page: https://github.com/lucas-flowers/snutree
Author: Lucas Flowers
Author-email: laf62@case.edu
License: GPLv3
Keywords: big little brother sister family tree
Platform: UNKNOWN
Classifier: Development Status :: 4 - Beta
Classifier: Intended Audience :: Other Audience
Classifier: Topic :: Other/Nonlisted Topic
Classifier: Topic :: Utilities
Classifier: License :: OSI Approved :: GNU General Public License v3 (GPLv3)
Classifier: Programming Language :: Python :: 3.5
Requires-Python: >=3.5
Requires-Dist: Cerberus
Requires-Dist: networkx (<2)
Requires-Dist: pluginbase
Requires-Dist: PyYAML
Requires-Dist: voluptuous
Provides-Extra: dev
Requires-Dist: pytest; extra == 'dev'
Requires-Dist: docutils; extra == 'dev'
Requires-Dist: pygments; extra == 'dev'
Requires-Dist: faker; extra == 'dev'
Requires-Dist: twine; extra == 'dev'
Provides-Extra: dot
Requires-Dist: pydotplus; extra == 'dot'
Provides-Extra: gui
Requires-Dist: gooey; extra == 'gui'
Requires-Dist: psutil; extra == 'gui'
Provides-Extra: sql
Requires-Dist: mysqlclient; extra == 'sql'
Provides-Extra: ssh
Requires-Dist: sshtunnel; extra == 'ssh'
